[{"signdate":"2022-04-01","retentiondate":"2022-04-02","retentionvalue":"100"},
{"signdate":"2022-04-01","retentiondate":"2022-04-03","retentionvalue":"99"},
{"signdate":"2022-04-01","retentiondate":"2022-04-04","retentionvalue":"98"},
{"signdate":"2022-04-01","retentiondate":"2022-04-05","retentionvalue":"97"},
{"signdate":"2022-04-01","retentiondate":"2022-04-06","retentionvalue":"96"},
{"signdate":"2022-04-01","retentiondate":"2022-04-07","retentionvalue":"10"},
{"signdate":"2022-04-01","retentiondate":"2022-04-08","retentionvalue":"94"},
{"signdate":"2022-04-01","retentiondate":"2022-04-09","retentionvalue":"93"},
{"signdate":"2022-04-01","retentiondate":"2022-04-10","retentionvalue":"92"},
{"signdate":"2022-04-01","retentiondate":"2022-04-11","retentionvalue":"90"},

{"signdate":"2022-04-02","retentiondate":"2022-04-03","retentionvalue":"90"},
{"signdate":"2022-04-02","retentiondate":"2022-04-04","retentionvalue":"90"},
{"signdate":"2022-04-02","retentiondate":"2022-04-05","retentionvalue":"90"},
{"signdate":"2022-04-02","retentiondate":"2022-04-06","retentionvalue":"90"},
{"signdate":"2022-04-02","retentiondate":"2022-04-07","retentionvalue":"90"},
{"signdate":"2022-04-02","retentiondate":"2022-04-08","retentionvalue":"22"},
{"signdate":"2022-04-02","retentiondate":"2022-04-09","retentionvalue":"21"},
{"signdate":"2022-04-02","retentiondate":"2022-04-10","retentionvalue":"34"},
{"signdate":"2022-04-02","retentiondate":"2022-04-11","retentionvalue":"55"},
{"signdate":"2022-04-02","retentiondate":"2022-04-12","retentionvalue":"22"},
{"signdate":"2022-04-02","retentiondate":"2022-04-13","retentionvalue":"34"},
{"signdate":"2022-04-02","retentiondate":"2022-04-14","retentionvalue":"24"},
{"signdate":"2022-04-02","retentiondate":"2022-04-15","retentionvalue":"93"},
{"signdate":"2022-04-02","retentiondate":"2022-04-16","retentionvalue":"11"},
{"signdate":"2022-04-02","retentiondate":"2022-04-17","retentionvalue":"20"},


{"signdate":"2022-04-03","retentiondate":"2022-04-04","retentionvalue":"98"},
{"signdate":"2022-04-03","retentiondate":"2022-04-05","retentionvalue":"97"},
{"signdate":"2022-04-03","retentiondate":"2022-04-06","retentionvalue":"96"},
{"signdate":"2022-04-03","retentiondate":"2022-04-07","retentionvalue":"94"},
{"signdate":"2022-04-03","retentiondate":"2022-04-08","retentionvalue":"93"},
{"signdate":"2022-04-03","retentiondate":"2022-04-09","retentionvalue":"88"},
{"signdate":"2022-04-03","retentiondate":"2022-04-10","retentionvalue":"79"},
{"signdate":"2022-04-03","retentiondate":"2022-04-11","retentionvalue":"76"},
{"signdate":"2022-04-03","retentiondate":"2022-04-12","retentionvalue":"72"},
{"signdate":"2022-04-03","retentiondate":"2022-04-13","retentionvalue":"70"},
{"signdate":"2022-04-03","retentiondate":"2022-04-14","retentionvalue":"65"},
{"signdate":"2022-04-03","retentiondate":"2022-04-15","retentionvalue":"60"},
{"signdate":"2022-04-03","retentiondate":"2022-04-16","retentionvalue":"55"},
{"signdate":"2022-04-03","retentiondate":"2022-04-17","retentionvalue":"52"},
{"signdate":"2022-04-03","retentiondate":"2022-04-18","retentionvalue":"50"},


{"signdate":"2022-04-04","retentiondate":"2022-04-05","retentionvalue":"90"},
{"signdate":"2022-04-04","retentiondate":"2022-04-06","retentionvalue":"90"},
{"signdate":"2022-04-04","retentiondate":"2022-04-07","retentionvalue":"90"},
{"signdate":"2022-04-04","retentiondate":"2022-04-08","retentionvalue":"90"},
{"signdate":"2022-04-04","retentiondate":"2022-04-09","retentionvalue":"90"},
{"signdate":"2022-04-04","retentiondate":"2022-04-10","retentionvalue":"22"},
{"signdate":"2022-04-04","retentiondate":"2022-04-11","retentionvalue":"21"},
{"signdate":"2022-04-04","retentiondate":"2022-04-12","retentionvalue":"34"},
{"signdate":"2022-04-04","retentiondate":"2022-04-13","retentionvalue":"55"},
{"signdate":"2022-04-04","retentiondate":"2022-04-14","retentionvalue":"22"},
{"signdate":"2022-04-04","retentiondate":"2022-04-15","retentionvalue":"34"},
{"signdate":"2022-04-04","retentiondate":"2022-04-16","retentionvalue":"24"},
{"signdate":"2022-04-04","retentiondate":"2022-04-17","retentionvalue":"93"},
{"signdate":"2022-04-04","retentiondate":"2022-04-18","retentionvalue":"11"},
{"signdate":"2022-04-04","retentiondate":"2022-04-19","retentionvalue":"20"},


{"signdate":"2022-04-05","retentiondate":"2022-04-06","retentionvalue":"92"},
{"signdate":"2022-04-05","retentiondate":"2022-04-07","retentionvalue":"90"},
{"signdate":"2022-04-05","retentiondate":"2022-04-08","retentionvalue":"88"},
{"signdate":"2022-04-05","retentiondate":"2022-04-09","retentionvalue":"87"},
{"signdate":"2022-04-05","retentiondate":"2022-04-10","retentionvalue":"86"},
{"signdate":"2022-04-05","retentiondate":"2022-04-11","retentionvalue":"80"},
{"signdate":"2022-04-05","retentiondate":"2022-04-12","retentionvalue":"77"},
{"signdate":"2022-04-05","retentiondate":"2022-04-13","retentionvalue":"65"},
{"signdate":"2022-04-05","retentiondate":"2022-04-14","retentionvalue":"35"},
{"signdate":"2022-04-05","retentiondate":"2022-04-15","retentionvalue":"32"},
{"signdate":"2022-04-05","retentiondate":"2022-04-16","retentionvalue":"30"},
{"signdate":"2022-04-05","retentiondate":"2022-04-17","retentionvalue":"24"},
{"signdate":"2022-04-05","retentiondate":"2022-04-18","retentionvalue":"21"},
{"signdate":"2022-04-05","retentiondate":"2022-04-19","retentionvalue":"11"},
{"signdate":"2022-04-05","retentiondate":"2022-04-20","retentionvalue":"10"}



]